{
  "lastChecks": {
    "weather": 1782600480000,
    "disk": 1782600120000,
    "git": 1782600480000,
    "memory": 1782600480000,
    "email": 1782600480000,
    "calendar": 1782600480000,
    "signal": 1782597339346,
    "embeddings": 1782597339346,
    "heartbeat": 1782600480000,
    "memory_maintenance": 1782601380000
  },
  "lastWeather": "Walling TN: Sunny +91°F, 54% humidity, ↗7mph wind, 0.00 in precip",
  "gitStatus": "workspace clean; patrickdanforth-site cleanup commit unpushed",
  "lastValues": {
    "weather": "Walling TN: Sunny +91°F, 54% humidity, ↗7mph wind, 0.00 in precip",
    "disk": "/dev/mapper/ubuntu--vg-ubuntu--lv   57G   33G   22G  61% /",
    "memory": "available 6.0Gi / total 7.7Gi",
    "git_clean": true,
    "git_status": "workspace clean; patrickdanforth-site cleanup commit unpushed due to dual-remote collision"
  },
  "notes": "Heartbeat 22:52 UTC. Weather +91°F sunny (wttr.in Walling TN), no change. Workspace clean. Email/calendar unavailable (no CLI configured). Memory maintenance not needed."
}
